parfor/__init__.py
parfor/pickler.py
parfor-2026.1.5.dist-info/licenses/LICENSE
parfor-2026.1.5.dist-info/METADATA
parfor-2026.1.5.dist-info/WHEEL
parfor-2026.1.5.dist-info/top_level.txt
parfor-2026.1.5.dist-info/RECORD
