Metadata-Version: 2.4
Name: parfor
Version: 2026.1.5
Summary: A package to mimic the use of parfor as done in Matlab.
Author-email: Wim Pomp-Pervova <wimpomp@gmail.com>
License: MIT
Project-URL: repository, https://github.com/wimpomp/parfor
Keywords: parfor,concurrency,multiprocessing,parallel
Requires-Python: >=3.10
License-File: LICENSE
Requires-Dist: dill>=0.3.0
Requires-Dist: numpy
Requires-Dist: tqdm>=4.50.0
Requires-Dist: ray
Provides-Extra: test
Requires-Dist: pytest; extra == "test"
Dynamic: license-file
